mcp_mysql/__init__.py
mcp_mysql/mcp_mysql.py
mcp_mysql/mcp_mysql_demo.py
mcp_mysql/mcp_mysql_env.py
mcp_mysql/mcp_mysql_server.py
mcp_mysql_nie-0.1.12.dist-info/METADATA
mcp_mysql_nie-0.1.12.dist-info/WHEEL
mcp_mysql_nie-0.1.12.dist-info/entry_points.txt
mcp_mysql_nie-0.1.12.dist-info/top_level.txt
mcp_mysql_nie-0.1.12.dist-info/RECORD
