Metadata-Version: 2.4
Name: mcp-mysql-nie
Version: 0.1.12
Summary: mysql server
Requires-Python: >=3.10
Requires-Dist: mcp[cli]>=1.9.4
Requires-Dist: mysql-connector-python>=8.0.34
